toplevel.py
toplevel-0.2.1.dist-info/DESCRIPTION.rst
toplevel-0.2.1.dist-info/METADATA
toplevel-0.2.1.dist-info/RECORD
toplevel-0.2.1.dist-info/WHEEL
toplevel-0.2.1.dist-info/entry_points.txt
toplevel-0.2.1.dist-info/metadata.json
toplevel-0.2.1.dist-info/top_level.txt
