Metadata-Version: 1.1
Name: toplevel
Version: 0.2.1
Summary: Validate toplevel imports against requirements.txt
Home-page: https://github.com/ohjeah/toplevel
Author: Markus Quade
Author-email: info@markusqua.de
License: MIT
Platform: UNKNOWN
Classifier: Programming Language :: Python
Classifier: Programming Language :: Python :: 3.5
Classifier: Programming Language :: Python :: 3.6
